ipqr/__init__.py
ipqr/ipqr.py
ipqr-0.1.1.dist-info/METADATA
ipqr-0.1.1.dist-info/WHEEL
ipqr-0.1.1.dist-info/entry_points.txt
ipqr-0.1.1.dist-info/top_level.txt
ipqr-0.1.1.dist-info/RECORD
