Metadata-Version: 2.1
Name: ipqr
Version: 0.1.1
Summary: A CLI tool to generate QR codes for local server URLs
Home-page: https://github.com/kasundularaam/ipqr
Author: Kasun Dulara
Author-email: kasundularaam@gmail.com
Classifier: Programming Language :: Python :: 3
Classifier: License :: OSI Approved :: MIT License
Classifier: Operating System :: OS Independent
Requires-Python: >=3.6
Requires-Dist: qrcode
Requires-Dist: netifaces
